npyi/__init__.py
npyi/exceptions.py
npyi/npi.py
tests/__init__.py
tests/test_npi.py
npyi-0.1.3.dist-info/LICENSE
npyi-0.1.3.dist-info/METADATA
npyi-0.1.3.dist-info/WHEEL
npyi-0.1.3.dist-info/top_level.txt
npyi-0.1.3.dist-info/RECORD
