Metadata-Version: 2.1
Name: npyi
Version: 0.1.3
Summary: API wrapper around the NPPES API
Home-page: https://github.com/andyh1203/npyi
Author: Andy Huynh
Author-email: andy.huynh312@gmail.com
License: BSD
Keywords: npyi,npi,nppes
Platform: UNKNOWN
Classifier: Development Status :: 4 - Beta
Classifier: Environment :: Console
Classifier: Intended Audience :: Developers
Classifier: Natural Language :: English
Classifier: License :: OSI Approved :: BSD License
Classifier: Programming Language :: Python
Classifier: Programming Language :: Python :: 2
Classifier: Programming Language :: Python :: 2.7
Classifier: Programming Language :: Python :: 3
Classifier: Programming Language :: Python :: 3.4
Classifier: Programming Language :: Python :: 3.5
Classifier: Programming Language :: Python :: 3.6
Classifier: Topic :: Software Development
Requires-Dist: requests (==2.21.0)
